buddy/__init__.py
buddy/client.py
buddy/command/__init__.py
buddy/command/stack.py
buddy/command/utils.py
buddy/command/cluster/__init__.py
buddy/command/cluster/service.py
buddy-0.0.3.dist-info/DESCRIPTION.rst
buddy-0.0.3.dist-info/METADATA
buddy-0.0.3.dist-info/RECORD
buddy-0.0.3.dist-info/WHEEL
buddy-0.0.3.dist-info/entry_points.txt
buddy-0.0.3.dist-info/metadata.json
buddy-0.0.3.dist-info/top_level.txt
