Metadata-Version: 2.0
Name: buddy
Version: 0.0.3
Summary: Buddy, your Cloudformation/ECS valet
Home-page: https://github.com/pior/buddy
Author: Pior Bastida
Author-email: pior@pbastida.net
License: MIT License
Keywords: aws cloudformation ecs deployment
Platform: Linux
Classifier: Development Status :: 3 - Alpha
Classifier: Environment :: Console
Classifier: Intended Audience :: Developers
Classifier: License :: OSI Approved :: MIT License
Classifier: Natural Language :: English
Classifier: Operating System :: POSIX :: Linux
Classifier: Programming Language :: Python
Classifier: Programming Language :: Python :: 3.5
Classifier: Programming Language :: Python :: Implementation :: CPython
Classifier: Topic :: System
Classifier: Topic :: Software Development
Requires-Dist: Arrow
Requires-Dist: boto3
Requires-Dist: click
Requires-Dist: pyyaml
Requires-Dist: tabulate
